exc2dic/__init__.py
exc2dic/read_dict.py
exc2dic/read_excel.py
excel2dict/__init__.py
excel2dict/read_dict.py
exc2dic-1.0.5.dist-info/METADATA
exc2dic-1.0.5.dist-info/WHEEL
exc2dic-1.0.5.dist-info/top_level.txt
exc2dic-1.0.5.dist-info/RECORD
