Metadata-Version: 2.1
Name: exc2dic
Version: 1.0.5
Summary: A package for reading Excel files
Home-page: https://github.com/MingyuanHuang/Excel2Dict
Author: Mingyuan
Author-email: mingyuanhuang@qq.com
Requires-Dist: pandas
